general_functions/__init__.py
general_functions/general_functions.py
general_functions-0.0.1.dist-info/METADATA
general_functions-0.0.1.dist-info/WHEEL
general_functions-0.0.1.dist-info/licenses/LICENSE
general_functions-0.0.1.dist-info/RECORD
